{
    "facts": [
        {
            "title": "GDP per Capita (Current US$)",
            "value": "20,972",
            "year": "2023",
            "source": "World Bank"
        },
        {
            "title": "Total Area",
            "value": "309,500 sq km",
            "year": "Current",
            "source": "Oman Data Portal"
        },
        {
            "title": "Capital City",
            "value": "Muscat",
            "year": "Current",
            "source": "Oman Data Portal"
        }
    ],
    "updated_at": "2025-12-04T01:39:52.176006"
}